CHANGELOG.rst
ranni/__init__.py
ranni-0.0.1.dev1.dist-info/LICENSE
ranni-0.0.1.dev1.dist-info/WHEEL
ranni-0.0.1.dev1.dist-info/METADATA
ranni-0.0.1.dev1.dist-info/RECORD
